MANIFEST.in
README.txt
setup.cfg
setup.py
wwp/__init__.py
wwp.theme.egg-info/PKG-INFO
wwp.theme.egg-info/SOURCES.txt
wwp.theme.egg-info/dependency_links.txt
wwp.theme.egg-info/entry_points.txt
wwp.theme.egg-info/namespace_packages.txt
wwp.theme.egg-info/not-zip-safe
wwp.theme.egg-info/paster_plugins.txt
wwp.theme.egg-info/requires.txt
wwp.theme.egg-info/top_level.txt
wwp/theme/__init__.py
wwp/theme/configure.zcml
wwp/theme/form.py
wwp/theme/profiles.zcml
wwp/theme/setuphandlers.py
wwp/theme/skins.zcml
wwp/theme/tests.py
wwp/theme/version.txt
wwp/theme/browser/__init__.py
wwp/theme/browser/configure.zcml
wwp/theme/browser/configure.zcml~
wwp/theme/browser/content.py
wwp/theme/browser/content.py~
wwp/theme/browser/feedback.py
wwp/theme/browser/footer.pt
wwp/theme/browser/interfaces.py
wwp/theme/browser/logging
wwp/theme/browser/navigation.py
wwp/theme/browser/navigation.py~
wwp/theme/browser/thankyou.py
wwp/theme/browser/viewlet.pt
wwp/theme/browser/viewlets.py
wwp/theme/browser/wwpdocument_actions.py
wwp/theme/browser/images/README.txt
wwp/theme/browser/lib/__init__.py
wwp/theme/browser/lib/wwpLib.py
wwp/theme/browser/stylesheets/README.txt
wwp/theme/browser/stylesheets/main.css
wwp/theme/browser/templates/WwpDate.pt
wwp/theme/browser/templates/document_actions.pt
wwp/theme/browser/templates/document_actions.pt~
wwp/theme/browser/templates/footer.pt
wwp/theme/browser/templates/logo.pt
wwp/theme/browser/templates/logo_footer.pt
wwp/theme/browser/templates/navigation.pt
wwp/theme/browser/templates/navigation.pt~
wwp/theme/browser/templates/navigation_recurse.pt
wwp/theme/browser/templates/thankyou.pt
wwp/theme/browser/templates/wwp_adsense_top.pt
wwp/theme/portlets/__init__.py
wwp/theme/portlets/configure.zcml
wwp/theme/portlets/navigation.pt
wwp/theme/portlets/navigation.py
wwp/theme/portlets/navigation_recurse.pt
wwp/theme/profiles/default/actionicons.xml
wwp/theme/profiles/default/actions.xml
wwp/theme/profiles/default/cssregistry.xml
wwp/theme/profiles/default/import_steps.xml
wwp/theme/profiles/default/metadata.xml
wwp/theme/profiles/default/propertiestool.xml
wwp/theme/profiles/default/skins.xml
wwp/theme/profiles/default/viewlets.xml
wwp/theme/profiles/default/wwp.theme_various.txt
wwp/theme/skins/wwp_theme_custom_images/bookmarklets.gif
