Metadata-Version: 1.0
Name: wwp.theme
Version: 1.8dev
Summary: WWP Legacy Theme
Home-page: http://wwp.greenwichmeantime.com/
Author: Peter Dyson
Author-email: pjdyson@gmail.com
License: GPL
Keywords: web zope plone WWP wwp theme
Platform: UNKNOWN
Classifier: Framework :: Plone
Classifier: Programming Language :: Python
Classifier: Topic :: Software Development :: Libraries :: Python Modules
